goe/__init__.py
goe/exceptions.py
goe/goe.py
goe/conductor/__init__.py
goe/conductor/hybrid_view_service.py
goe/config/__init__.py
goe/config/config_file.py
goe/config/config_validation_functions.py
goe/config/option_descriptions.py
goe/config/orchestration_config.py
goe/config/orchestration_defaults.py
goe/connect/__init__.py
goe/connect/connect.py
goe/connect/connect_backend.py
goe/connect/connect_constants.py
goe/connect/connect_frontend.py
goe/connect/connect_functions.py
goe/connect/connect_transport.py
goe/filesystem/__init__.py
goe/filesystem/cli_hdfs.py
goe/filesystem/goe_azure.py
goe/filesystem/goe_dfs.py
goe/filesystem/goe_dfs_factory.py
goe/filesystem/goe_gcs.py
goe/filesystem/goe_s3.py
goe/filesystem/web_hdfs.py
goe/listener/__init__.py
goe/listener/__main__.py
goe/listener/asgi.py
goe/listener/heartbeat.py
goe/listener/prestart.py
goe/listener/worker.py
goe/listener/wsgi.py
goe/listener/api/__init__.py
goe/listener/api/routes/__init__.py
goe/listener/api/routes/docs.py
goe/listener/api/routes/orchestration.py
goe/listener/api/routes/system.py
goe/listener/config/__init__.py
goe/listener/config/application.py
goe/listener/config/gunicorn.conf.py
goe/listener/config/logging.py
goe/listener/config/router.py
goe/listener/core/__init__.py
goe/listener/core/enum.py
goe/listener/core/events.py
goe/listener/core/security.py
goe/listener/core/worker.py
goe/listener/core/middleware/__init__.py
goe/listener/core/middleware/compression.py
goe/listener/core/middleware/cors.py
goe/listener/core/middleware/secure_headers.py
goe/listener/exceptions/__init__.py
goe/listener/exceptions/base.py
goe/listener/exceptions/errors.py
goe/listener/schemas/__init__.py
goe/listener/schemas/base.py
goe/listener/schemas/error.py
goe/listener/schemas/generics.py
goe/listener/schemas/orchestration.py
goe/listener/schemas/system.py
goe/listener/services/__init__.py
goe/listener/services/heartbeat.py
goe/listener/services/hybrid_view.py
goe/listener/services/orchestrate.py
goe_framework-1.0.9.dist-info/licenses/AUTHORS
goe_framework-1.0.9.dist-info/licenses/LICENSE
goe_framework-1.0.9.dist-info/METADATA
goe_framework-1.0.9.dist-info/WHEEL
goe_framework-1.0.9.dist-info/top_level.txt
goe_framework-1.0.9.dist-info/RECORD
