Metadata-Version: 2.4
Name: goe-framework
Version: 1.0.9
Maintainer-email: Neil Johnson <neiljohnson@google.com>
Project-URL: Homepage, https://github.com/gluent/goe
Project-URL: Issues, https://github.com/gluent/goe/issues
Classifier: Development Status :: 4 - Beta
Classifier: Programming Language :: Python :: 3.7
Classifier: Programming Language :: Python :: 3.8
Classifier: Programming Language :: Python :: 3.9
Classifier: Programming Language :: Python :: 3.10
Classifier: Programming Language :: Python :: 3.11
Classifier: Operating System :: OS Independent
Requires-Python: >=3.7
License-File: LICENSE
License-File: AUTHORS
Requires-Dist: pyarrow
Requires-Dist: avro
Requires-Dist: configparser
Requires-Dist: cryptography
Requires-Dist: filelock
Requires-Dist: lark-parser
Requires-Dist: numpy
Requires-Dist: orjson
Requires-Dist: python-dateutil
Requires-Dist: PyYAML
Requires-Dist: requests
Requires-Dist: termcolor
Requires-Dist: urllib3
Requires-Dist: fsspec[gcs]
Requires-Dist: google-cloud-storage
Requires-Dist: boto3
Requires-Dist: azure-common
Requires-Dist: azure-storage-blob
Requires-Dist: cx-Oracle
Requires-Dist: google-cloud-bigquery
Requires-Dist: google-cloud-kms
Requires-Dist: python-dotenv
Requires-Dist: fastapi==0.77.0
Requires-Dist: uvicorn==0.17.6
Requires-Dist: redis==4.4.4
Requires-Dist: gunicorn==20.1.0
Requires-Dist: brotli==1.0.9
Requires-Dist: tenacity==8.0.1
Requires-Dist: uvloop
Requires-Dist: httptools
Provides-Extra: hadoop
Requires-Dist: hdfs; extra == "hadoop"
Requires-Dist: impyla; extra == "hadoop"
Requires-Dist: requests-kerberos; extra == "hadoop"
Requires-Dist: thrift-sasl; extra == "hadoop"
Provides-Extra: snowflake
Requires-Dist: snowflake-connector-python; extra == "snowflake"
Provides-Extra: sql-server
Requires-Dist: pymssql; extra == "sql-server"
Provides-Extra: synapse
Requires-Dist: pyodbc; extra == "synapse"
Provides-Extra: teradata
Requires-Dist: pyodbc; extra == "teradata"
Provides-Extra: dev
Requires-Dist: black; extra == "dev"
Requires-Dist: nox; extra == "dev"
Requires-Dist: pytest; extra == "dev"
Requires-Dist: pytest-xdist; extra == "dev"
Provides-Extra: test
Requires-Dist: nox; extra == "test"
Requires-Dist: pytest; extra == "test"
Requires-Dist: pytest-xdist; extra == "test"
Dynamic: license-file
